peakrdl_python/.coveragerc
peakrdl_python/__about__.py
peakrdl_python/__init__.py
peakrdl_python/__peakrdl__.py
peakrdl_python/_deploy_package.py
peakrdl_python/_node_walkers.py
peakrdl_python/class_names.py
peakrdl_python/compiler_udp.py
peakrdl_python/exporter.py
peakrdl_python/py.typed
peakrdl_python/safe_name_utility.py
peakrdl_python/systemrdl_node_hashes.py
peakrdl_python/systemrdl_node_utility_functions.py
peakrdl_python/unique_component_iterator.py
peakrdl_python/lib/__init__.py
peakrdl_python/lib/async_memory.py
peakrdl_python/lib/async_register_and_field.py
peakrdl_python/lib/base.py
peakrdl_python/lib/base_field.py
peakrdl_python/lib/base_register.py
peakrdl_python/lib/callbacks.py
peakrdl_python/lib/field_encoding.py
peakrdl_python/lib/memory.py
peakrdl_python/lib/py.typed
peakrdl_python/lib/register_and_field.py
peakrdl_python/lib/sections.py
peakrdl_python/lib/utility_functions.py
peakrdl_python/sim_lib/__init__.py
peakrdl_python/sim_lib/_callbacks.py
peakrdl_python/sim_lib/base.py
peakrdl_python/sim_lib/dummy_callbacks.py
peakrdl_python/sim_lib/field.py
peakrdl_python/sim_lib/memory.py
peakrdl_python/sim_lib/py.typed
peakrdl_python/sim_lib/register.py
peakrdl_python/sim_lib/simulator.py
peakrdl_python/templates/__init__.py
peakrdl_python/templates/addrmap.py.jinja
peakrdl_python/templates/addrmap_field.py.jinja
peakrdl_python/templates/addrmap_memory.py.jinja
peakrdl_python/templates/addrmap_register.py.jinja
peakrdl_python/templates/addrmap_simulation.py.jinja
peakrdl_python/templates/addrmap_simulation_tb.py.jinja
peakrdl_python/templates/addrmap_system_rdl_name_mapping.py.jinja
peakrdl_python/templates/addrmap_tb.py.jinja
peakrdl_python/templates/addrmap_udp_property.py.jinja
peakrdl_python/templates/addrmap_universal_property.py.jinja
peakrdl_python/templates/baseclass_simulation_tb.py.jinja
peakrdl_python/templates/baseclass_tb.py.jinja
peakrdl_python/templates/child_definitions.py.jinja
peakrdl_python/templates/example.py.jinja
peakrdl_python-2.2.0.dist-info/licenses/LICENSE
peakrdl_python-2.2.0.dist-info/METADATA
peakrdl_python-2.2.0.dist-info/WHEEL
peakrdl_python-2.2.0.dist-info/entry_points.txt
peakrdl_python-2.2.0.dist-info/top_level.txt
peakrdl_python-2.2.0.dist-info/RECORD
