Metadata-Version: 2.4
Name: peakrdl-python
Version: 2.2.0
Summary: Generate Python Register Access Layer (RAL) from SystemRDL
Author: Keith Brady
License:              GNU LESSER GENERAL PUBLIC LICENSE
Project-URL: Source, https://github.com/krcb197/PeakRDL-python
Project-URL: Tracker, https://github.com/krcb197/PeakRDL-python/issues
Project-URL: Documentation, https://peakrdl-python.readthedocs.io/
Project-URL: Changelog, https://github.com/krcb197/PeakRDL-python/releases
Keywords: SystemRDL,PeakRDL,CSR,compiler,tool,registers,generator,Python
Classifier: Development Status :: 5 - Production/Stable
Classifier: Programming Language :: Python
Classifier: Programming Language :: Python :: 3
Classifier: Programming Language :: Python :: 3.9
Classifier: Programming Language :: Python :: 3.10
Classifier: Programming Language :: Python :: 3.11
Classifier: Programming Language :: Python :: 3.12
Classifier: Programming Language :: Python :: 3.13
Classifier: Programming Language :: Python :: 3.14
Classifier: Programming Language :: Python :: 3 :: Only
Classifier: Intended Audience :: Developers
Classifier: License :: OSI Approved :: GNU Lesser General Public License v3 (LGPLv3)
Classifier: Operating System :: OS Independent
Classifier: Topic :: Scientific/Engineering :: Electronic Design Automation (EDA)
Classifier: Typing :: Typed
Requires-Python: >=3.9.2
License-File: LICENSE
Requires-Dist: systemrdl-compiler>=1.29.3
Requires-Dist: jinja2
Requires-Dist: typing-extensions; python_version < "3.11"
Requires-Dist: more_itertools; python_version < "3.13"
Provides-Extra: dev
Requires-Dist: mypy; extra == "dev"
Requires-Dist: pylint; extra == "dev"
Requires-Dist: coverage; extra == "dev"
Requires-Dist: peakrdl; extra == "dev"
Provides-Extra: peakrdl
Requires-Dist: peakrdl; extra == "peakrdl"
Provides-Extra: unit-test
Requires-Dist: peakrdl; extra == "unit-test"
Requires-Dist: tomli; python_version < "3.11" and extra == "unit-test"
Dynamic: license-file
